xmlkit/__init__.py
xmlkit/py.typed
xmlkit/types.py
xmlkit-0.0.2.dist-info/licenses/LICENCE
xmlkit-0.0.2.dist-info/METADATA
xmlkit-0.0.2.dist-info/WHEEL
xmlkit-0.0.2.dist-info/entry_points.txt
xmlkit-0.0.2.dist-info/top_level.txt
xmlkit-0.0.2.dist-info/RECORD
