Metadata-Version: 2.4
Name: xmlKit
Version: 0.0.2
Summary: A fork of xmltodict to add new features. Makes working with XML feel like you are working with JSON
Author: Martin Blech, K-TEC Systems Ltd
License-Expression: MIT
Project-URL: Homepage, https://gitlab.com/k-tec/xmlKit
Project-URL: Company, https://k-tec.uk/
Classifier: Intended Audience :: Developers
Classifier: Operating System :: OS Independent
Classifier: Programming Language :: Python
Classifier: Programming Language :: Python :: 3
Classifier: Programming Language :: Python :: 3.12
Classifier: Programming Language :: Python :: 3.13
Classifier: Programming Language :: Python :: 3.14
Classifier: Programming Language :: Python :: Implementation :: PyPy
Classifier: Topic :: Text Processing :: Markup :: XML
Requires-Python: >=3.12
License-File: LICENCE
Dynamic: license-file
